vbvarsel/__init__.py
vbvarsel/calcparams.py
vbvarsel/custodian.py
vbvarsel/data_sim_crook.py
vbvarsel/elbo.py
vbvarsel/experiment_data.py
vbvarsel/global_parameters.py
vbvarsel/vbvarsel.py
vbvarsel-0.2.3.dist-info/LICENSE
vbvarsel-0.2.3.dist-info/METADATA
vbvarsel-0.2.3.dist-info/WHEEL
vbvarsel-0.2.3.dist-info/top_level.txt
vbvarsel-0.2.3.dist-info/RECORD
