Metadata-Version: 2.1
Name: vbvarsel
Version: 0.2.3
Summary: Quickly identify clusters of variables by using a scalable, computationally efficienty annealed variational Bayesian algorithm.
Author-email: Alan Nardo <alan.nardo@mrc-bsu.cam.ac.uk>, Paul Kirk <paul.kirk@mrc-bsu.cam.ac.uk>, Emma Prevot <prevot.emma@icloud.com>, Rory Toogood <iiauthor@gmail.com>, Filippo Pagani <filippo.pagani@mrc-bsu.cam.ac.uk>
License:                     GNU GENERAL PUBLIC LICENSE
Project-URL: Repository, https://github.com/MRCBSU/vbvarsel
Project-URL: Issues, https://github.com/MRCBSU/vbvarsel/issues
Project-URL: Changelog, https://github.com/MRCBSU/vbvarsel/CHANGELOG.md
Project-URL: ReadTheDocs, https://vbvarsel.readthedocs.io
Keywords: statistics,clustering
Classifier: Development Status :: 2 - Pre-Alpha
Classifier: Intended Audience :: Developers
Classifier: Intended Audience :: Science/Research
Classifier: Natural Language :: English
Classifier: Programming Language :: Python :: 3
Classifier: Programming Language :: Python :: 3.10
Classifier: Programming Language :: Python :: 3.11
Classifier: Programming Language :: Python :: 3.12
Requires-Python: >=3.8
License-File: LICENSE
Requires-Dist: numpy>=2.0.1
Requires-Dist: pandas>=2.2.2
Requires-Dist: scikit-learn>=1.5.1
Requires-Dist: scipy>=1.14.0
Requires-Dist: typing>=3.7.4.3
Provides-Extra: dev
Requires-Dist: build; extra == "dev"
Requires-Dist: bump-my-version; extra == "dev"
Requires-Dist: coverage[toml]; extra == "dev"
Requires-Dist: pytest; extra == "dev"
Requires-Dist: pytest-cov; extra == "dev"
Requires-Dist: ruff; extra == "dev"
Requires-Dist: sphinx; extra == "dev"
Requires-Dist: sphinx_rtd_theme; extra == "dev"
Requires-Dist: sphinx-autoapi; extra == "dev"
Requires-Dist: tox; extra == "dev"
Requires-Dist: myst_parser; extra == "dev"
Provides-Extra: docs
Requires-Dist: sphinx; extra == "docs"
Requires-Dist: sphinx_rtd_theme; extra == "docs"
Requires-Dist: sphinx-autoapi; extra == "docs"
Requires-Dist: myst_parser; extra == "docs"
Provides-Extra: publishing
Requires-Dist: build; extra == "publishing"
Requires-Dist: twine; extra == "publishing"
Requires-Dist: wheel; extra == "publishing"
